thonnycontrib/block_highlight/__init__.py
thonnytn_block_highlight-0.3.1.dist-info/METADATA
thonnytn_block_highlight-0.3.1.dist-info/WHEEL
thonnytn_block_highlight-0.3.1.dist-info/top_level.txt
thonnytn_block_highlight-0.3.1.dist-info/RECORD
